odoo/addons/delivery_sendcloud_oca/README.rst
odoo/addons/delivery_sendcloud_oca/__init__.py
odoo/addons/delivery_sendcloud_oca/__manifest__.py
odoo/addons/delivery_sendcloud_oca/controllers/__init__.py
odoo/addons/delivery_sendcloud_oca/controllers/main.py
odoo/addons/delivery_sendcloud_oca/data/delivery_sendcloud_cron.xml
odoo/addons/delivery_sendcloud_oca/data/delivery_sendcloud_data.xml
odoo/addons/delivery_sendcloud_oca/data/onboarding_data.xml
odoo/addons/delivery_sendcloud_oca/i18n/delivery_sendcloud_oca.pot
odoo/addons/delivery_sendcloud_oca/i18n/it.po
odoo/addons/delivery_sendcloud_oca/models/__init__.py
odoo/addons/delivery_sendcloud_oca/models/abstract_sendcloud_mixin.py
odoo/addons/delivery_sendcloud_oca/models/abstract_sendcloud_request.py
odoo/addons/delivery_sendcloud_oca/models/delivery_carrier.py
odoo/addons/delivery_sendcloud_oca/models/onboarding_onboarding.py
odoo/addons/delivery_sendcloud_oca/models/onboarding_onboarding_step.py
odoo/addons/delivery_sendcloud_oca/models/res_company.py
odoo/addons/delivery_sendcloud_oca/models/res_config_settings.py
odoo/addons/delivery_sendcloud_oca/models/res_partner.py
odoo/addons/delivery_sendcloud_oca/models/sale_order.py
odoo/addons/delivery_sendcloud_oca/models/sendcloud_action.py
odoo/addons/delivery_sendcloud_oca/models/sendcloud_brand.py
odoo/addons/delivery_sendcloud_oca/models/sendcloud_carrier.py
odoo/addons/delivery_sendcloud_oca/models/sendcloud_integration.py
odoo/addons/delivery_sendcloud_oca/models/sendcloud_invoice.py
odoo/addons/delivery_sendcloud_oca/models/sendcloud_invoice_item.py
odoo/addons/delivery_sendcloud_oca/models/sendcloud_parcel.py
odoo/addons/delivery_sendcloud_oca/models/sendcloud_parcel_item.py
odoo/addons/delivery_sendcloud_oca/models/sendcloud_parcel_status.py
odoo/addons/delivery_sendcloud_oca/models/sendcloud_return.py
odoo/addons/delivery_sendcloud_oca/models/sendcloud_return_location.py
odoo/addons/delivery_sendcloud_oca/models/sendcloud_sender_address.py
odoo_addon_delivery_sendcloud_oca-17.0.1.0.0.3.dist-info/METADATA
odoo_addon_delivery_sendcloud_oca-17.0.1.0.0.3.dist-info/WHEEL
odoo_addon_delivery_sendcloud_oca-17.0.1.0.0.3.dist-info/top_level.txt
odoo_addon_delivery_sendcloud_oca-17.0.1.0.0.3.dist-info/RECORD
