Metadata-Version: 2.1
Name: odoo-addon-delivery_sendcloud_oca
Version: 17.0.1.0.0.3
Requires-Python: >=3.10
Requires-Dist: odoo>=17.0a,<17.1dev
Summary: Compute shipping costs and ship with Sendcloud
Home-page: https://github.com/OCA/delivery-carrier
License: LGPL-3
Author: Onestein,Odoo Community Association (OCA)
Author-email: support@odoo-community.org
Classifier: Programming Language :: Python
Classifier: Framework :: Odoo
Classifier: Framework :: Odoo :: 17.0
Classifier: License :: OSI Approved :: GNU Lesser General Public License v3 (LGPLv3)
